algobin.py
algobin-0.0.2.dist-info/LICENSE
algobin-0.0.2.dist-info/METADATA
algobin-0.0.2.dist-info/WHEEL
algobin-0.0.2.dist-info/top_level.txt
algobin-0.0.2.dist-info/RECORD
