Metadata-Version: 2.1
Name: algobin
Version: 0.0.2
Summary: Basic trading operations of binance to be used in algorithmic trading.
Home-page: https://github.com/aticio/algobin
Author: Özgür Atıcı
Author-email: aticiozgur@gmail.com
License: UNKNOWN
Platform: UNKNOWN
Classifier: Programming Language :: Python :: 3
Classifier: License :: OSI Approved :: MIT License
Classifier: Operating System :: OS Independent
Requires-Dist: algoutils
Requires-Dist: requests
Provides-Extra: dev
Requires-Dist: pytest (>=3.7) ; extra == 'dev'
